sample/__init__.py
sample/package_data.dat
sample/simple.py
oxlogger-1.0.1.dist-info/LICENSE.txt
oxlogger-1.0.1.dist-info/METADATA
oxlogger-1.0.1.dist-info/WHEEL
oxlogger-1.0.1.dist-info/entry_points.txt
oxlogger-1.0.1.dist-info/top_level.txt
oxlogger-1.0.1.dist-info/RECORD
