Metadata-Version: 2.1
Name: oxlogger
Version: 1.0.1
Summary: Placeholder Python Project to prevent dependency confusion
Author-email: OX Security <contact@ox.security>
Maintainer-email: OX Security <contact@ox.security>
License: Copyright (c) 2016 The Python Packaging Authority (PyPA)
Project-URL: Homepage, https://github.com/oxsecurity/oxlogger
Project-URL: Bug Reports, https://github.com/oxsecurity/oxlogger/issues
Project-URL: Source, https://github.com/oxsecurity/oxlogger
Keywords: ox.security,OX Security,Dependency Confusion
Classifier: Development Status :: 3 - Alpha
Classifier: Intended Audience :: Developers
Classifier: Topic :: Software Development :: Build Tools
Classifier: License :: OSI Approved :: MIT License
Classifier: Programming Language :: Python :: 3
Classifier: Programming Language :: Python :: 3.7
Classifier: Programming Language :: Python :: 3.8
Classifier: Programming Language :: Python :: 3.9
Classifier: Programming Language :: Python :: 3.10
Classifier: Programming Language :: Python :: 3.11
Classifier: Programming Language :: Python :: 3 :: Only
Requires-Python: >=3.7
License-File: LICENSE.txt
Requires-Dist: peppercorn
Provides-Extra: dev
Requires-Dist: check-manifest ; extra == 'dev'
Provides-Extra: test
Requires-Dist: coverage ; extra == 'test'
